{
  "errno": 0,
  "errmsg": "",
  "result": {
    "page": {
      "pagesize": "10",
      "comm_total": 40
    },
    "comm": [
      {
        "user_link": "http://i.360.cn/profile/viewuinfo/u/360U2568988452",
        "imageUrl": "http://p1.qhmsg.com/dm/48_48_100/t00df551a583a87f4e9.jpg",
        "username": "360U2568988452",
        "comment_level": "5",
        "order_id": "151029092******8452",
        "comment_content": "我的录音终于找回来了",
        "reply": [],
        "comment_create_time": "2015-10-29 09:55:47",
        "product_name": "U盘，SD卡，内存卡，数据恢复与维修",
        "sub_comm": [],
        "sub_reply": []
      },
      {
        "user_link": "http://i.360.cn/profile/viewuinfo/u/360U2568988452",
        "imageUrl": "http://p1.qhmsg.com/dm/48_48_100/t00df551a583a87f4e9.jpg",
        "username": "360U2568988452",
        "comment_level": "5",
        "order_id": "151029092******8452",
        "comment_content": "珍贵的照片都找回来了，很满意",
        "reply": [],
        "comment_create_time": "2015-10-29 09:50:38",
        "product_name": "U盘，SD卡，内存卡，数据恢复与维修",
        "sub_comm": [],
        "sub_reply": []
      },
      {
        "user_link": "http://i.360.cn/profile/viewuinfo/u/360U1038189955",
        "imageUrl": "http://p1.qhmsg.com/dm/48_48_100/t00df551a583a87f4e9.jpg",
        "username": "360U1038189955",
        "comment_level": "5",
        "order_id": "151029092******9955",
        "comment_content": "谢谢老板，来了第三次了还有折扣！",
        "reply": [],
        "comment_create_time": "2015-10-29 09:44:18",
        "product_name": "电脑温度高，除尘清灰",
        "sub_comm": [],
        "sub_reply": []
      },
      {
        "user_link": "http://i.360.cn/profile/viewuinfo/u/360U1038189955",
        "imageUrl": "http://p1.qhmsg.com/dm/48_48_100/t00df551a583a87f4e9.jpg",
        "username": "360U1038189955",
        "comment_level": "5",
        "order_id": "151029092******9955",
        "comment_content": "整的很有效果，原来笔记本清灰有这么大的好处，受教了！",
        "reply": [],
        "comment_create_time": "2015-10-29 09:42:10",
        "product_name": "电脑温度高，除尘清灰",
        "sub_comm": [],
        "sub_reply": []
      },
      {
        "user_link": "http://i.360.cn/profile/viewuinfo/u/360U374454624",
        "imageUrl": "http://p1.qhmsg.com/dm/48_48_100/t012d8d20d681a99e3e.jpg",
        "username": "360U374454624",
        "comment_level": "5",
        "order_id": "151029092******4624",
        "comment_content": "非常满意的一次维修体验，店家的系统装的很好！",
        "reply": [],
        "comment_create_time": "2015-10-29 09:36:42",
        "product_name": "电脑温度高，除尘清灰",
        "sub_comm": [],
        "sub_reply": []
      },
      {
        "user_link": "http://i.360.cn/profile/viewuinfo/u/360U374454624",
        "imageUrl": "http://p1.qhmsg.com/dm/48_48_100/t012d8d20d681a99e3e.jpg",
        "username": "360U374454624",
        "comment_level": "5",
        "order_id": "151029092******4624",
        "comment_content": "十分满意。店家非常热心",
        "reply": [],
        "comment_create_time": "2015-10-29 09:34:36",
        "product_name": "上门维修电脑",
        "sub_comm": [],
        "sub_reply": []
      },
      {
        "user_link": "http://i.360.cn/profile/viewuinfo/u/360U374454624",
        "imageUrl": "http://p1.qhmsg.com/dm/48_48_100/t012d8d20d681a99e3e.jpg",
        "username": "360U374454624",
        "comment_level": "5",
        "order_id": "151029092******4624",
        "comment_content": "非常满意",
        "reply": [],
        "comment_create_time": "2015-10-29 09:31:38",
        "product_name": "上门维修电脑",
        "sub_comm": [],
        "sub_reply": []
      },
      {
        "user_link": "http://i.360.cn/profile/viewuinfo/u/360U1504936197",
        "imageUrl": "http://p1.qhmsg.com/dm/48_48_100/t00df551a583a87f4e9.jpg",
        "username": "360U1504936197",
        "comment_level": "5",
        "order_id": "150629012******5828",
        "comment_content": "好！",
        "reply": [],
        "comment_create_time": "2015-06-29 14:16:29",
        "product_name": "【69元清灰活动】笔记本除尘清洁保养",
        "sub_comm": [],
        "sub_reply": []
      },
      {
        "user_link": "http://i.360.cn/profile/viewuinfo/u/",
        "imageUrl": "",
        "username": "",
        "comment_level": "5",
        "order_id": "141220162******2600",
        "comment_content": "服务很给力很专业！&nbsp;商家很负责，问题得到解决！&nbsp;问题得到很好的解决，赞！",
        "reply": [],
        "comment_create_time": "2014-12-20 17:46:37",
        "product_name": "【29.9元清灰活动】笔记本除尘清洁保养",
        "sub_comm": [],
        "sub_reply": []
      },
      {
        "user_link": "http://i.360.cn/profile/viewuinfo/u/",
        "imageUrl": "",
        "username": "",
        "comment_level": "5",
        "order_id": "141121102******8630",
        "comment_content": "服务很给力很专业！&nbsp;商家很负责，问题得到解决！&nbsp;问题得到很好的解决，赞！",
        "reply": [],
        "comment_create_time": "2014-11-21 20:15:33",
        "product_name": "软件数据恢复",
        "sub_comm": [],
        "sub_reply": []
      }
    ]
  }
}